ypp/__init__.py
ypp/__main__.py
ypp/auto_build.py
ypp/common.py
ypp/feedback_export.py
ypp/init_commands.py
ypp/makefile_modifier.py
ypp/port_mapping.py
ypp/port_who.py
ypp/ppt_attributes.py
ypp/sync_watch.py
ypp/vscode_config.py
ypp/wsl_port_forward.py
ypp-0.3.29.dist-info/licenses/LICENSE
ypp-0.3.29.dist-info/METADATA
ypp-0.3.29.dist-info/WHEEL
ypp-0.3.29.dist-info/entry_points.txt
ypp-0.3.29.dist-info/top_level.txt
ypp-0.3.29.dist-info/RECORD
