Metadata-Version: 2.4
Name: ypp
Version: 0.3.29
Summary: 多分支 worktree 管理工具
Author: ypp
License: MIT
Keywords: git,worktree,krepo-ng,cli
Classifier: Programming Language :: Python :: 3
Classifier: Operating System :: OS Independent
Classifier: Environment :: Console
Classifier: Topic :: Software Development :: Version Control :: Git
Requires-Python: >=3.8
License-File: LICENSE
Dynamic: license-file
